[{"arguments":["clang","-Wno-documentation-unknown-command","-Wno-unknown-warning-option","-Wno-unknown-pragmas","-nostdinc","-nostdinc++","-DQT_QML_DEBUG","-g","-std=gnu++17","-fdiagnostics-color=always","-fsyntax-only","-m64","--target=x86_64-w64-mingw32","-DMINGW_HAS_SECURE_API","-DQT_CORE_LIB","-DQT_GUI_LIB","-DQT_NEEDS_QMAIN","-DQT_WIDGETS_LIB","-DUNICODE","-DWIN32","-DWIN64","-D_ENABLE_EXTENDED_ALIGNED_STORAGE","-D_UNICODE","-D_WIN64","-DQ_CREATOR_RUN","-DQT_ANNOTATE_FUNCTION(x)=__attribute__((annotate(#x)))","-IC:\\thely\\Qt\\Tools\\QtCreator\\share\\qtcreator\\cplusplus\\wrappedMingwHeaders","-IC:\\thely\\Qt\\Tools\\QtCreator\\share\\qtcreator\\cplusplus\\wrappedQtHeaders","-IC:\\thely\\Qt\\Tools\\QtCreator\\share\\qtcreator\\cplusplus\\wrappedQtHeaders\\QtCore","-IC:\\msys64\\home\\dyl\\Codes\\qt\\Snake\\build\\Desktop_Qt_6_7_3_MinGW_64_bit-Debug\\Snake_autogen\\include","-isystem","C:\\thely\\Qt\\6.7.3\\mingw_64\\include\\QtCore","-isystem","C:\\thely\\Qt\\6.7.3\\mingw_64\\include","-isystem","C:\\thely\\Qt\\6.7.3\\mingw_64\\mkspecs\\win32-g++","-isystem","C:\\thely\\Qt\\6.7.3\\mingw_64\\include\\QtWidgets","-isystem","C:\\thely\\Qt\\6.7.3\\mingw_64\\include\\QtGui","-isystem","C:\\thely\\Qt\\Tools\\mingw1120_64\\lib\\gcc\\x86_64-w64-mingw32\\11.2.0\\include\\c++","-isystem","C:\\thely\\Qt\\Tools\\mingw1120_64\\lib\\gcc\\x86_64-w64-mingw32\\11.2.0\\include\\c++\\x86_64-w64-mingw32","-isystem","C:\\thely\\Qt\\Tools\\mingw1120_64\\lib\\gcc\\x86_64-w64-mingw32\\11.2.0\\include\\c++\\backward","-isystem","C:\\thely\\Qt\\Tools\\QtCreator\\bin\\clang\\lib\\clang\\18\\include","-isystem","C:\\thely\\Qt\\Tools\\mingw1120_64\\x86_64-w64-mingw32\\include","-fmessage-length=0","-fdiagnostics-show-note-include-stack","-fretain-comments-from-system-headers","-fmacro-backtrace-limit=0","-ferror-limit=1000","-x","c++","C:\\msys64\\home\\dyl\\Codes\\qt\\Snake\\main.cpp"],"directory":"C:/msys64/home/dyl/Codes/qt/Snake/build/Desktop_Qt_6_7_3_MinGW_64_bit-Debug/.qtc_clangd","file":"C:/msys64/home/dyl/Codes/qt/Snake/main.cpp"},{"arguments":["clang","-Wno-documentation-unknown-command","-Wno-unknown-warning-option","-Wno-unknown-pragmas","-nostdinc","-nostdinc++","-DQT_QML_DEBUG","-g","-std=gnu++17","-fdiagnostics-color=always","-fsyntax-only","-m64","--target=x86_64-w64-mingw32","-DMINGW_HAS_SECURE_API","-DQT_CORE_LIB","-DQT_GUI_LIB","-DQT_NEEDS_QMAIN","-DQT_WIDGETS_LIB","-DUNICODE","-DWIN32","-DWIN64","-D_ENABLE_EXTENDED_ALIGNED_STORAGE","-D_UNICODE","-D_WIN64","-DQ_CREATOR_RUN","-DQT_ANNOTATE_FUNCTION(x)=__attribute__((annotate(#x)))","-IC:\\thely\\Qt\\Tools\\QtCreator\\share\\qtcreator\\cplusplus\\wrappedMingwHeaders","-IC:\\thely\\Qt\\Tools\\QtCreator\\share\\qtcreator\\cplusplus\\wrappedQtHeaders","-IC:\\thely\\Qt\\Tools\\QtCreator\\share\\qtcreator\\cplusplus\\wrappedQtHeaders\\QtCore","-IC:\\msys64\\home\\dyl\\Codes\\qt\\Snake\\build\\Desktop_Qt_6_7_3_MinGW_64_bit-Debug\\Snake_autogen\\include","-isystem","C:\\thely\\Qt\\6.7.3\\mingw_64\\include\\QtCore","-isystem","C:\\thely\\Qt\\6.7.3\\mingw_64\\include","-isystem","C:\\thely\\Qt\\6.7.3\\mingw_64\\mkspecs\\win32-g++","-isystem","C:\\thely\\Qt\\6.7.3\\mingw_64\\include\\QtWidgets","-isystem","C:\\thely\\Qt\\6.7.3\\mingw_64\\include\\QtGui","-isystem","C:\\thely\\Qt\\Tools\\mingw1120_64\\lib\\gcc\\x86_64-w64-mingw32\\11.2.0\\include\\c++","-isystem","C:\\thely\\Qt\\Tools\\mingw1120_64\\lib\\gcc\\x86_64-w64-mingw32\\11.2.0\\include\\c++\\x86_64-w64-mingw32","-isystem","C:\\thely\\Qt\\Tools\\mingw1120_64\\lib\\gcc\\x86_64-w64-mingw32\\11.2.0\\include\\c++\\backward","-isystem","C:\\thely\\Qt\\Tools\\QtCreator\\bin\\clang\\lib\\clang\\18\\include","-isystem","C:\\thely\\Qt\\Tools\\mingw1120_64\\x86_64-w64-mingw32\\include","-fmessage-length=0","-fdiagnostics-show-note-include-stack","-fretain-comments-from-system-headers","-fmacro-backtrace-limit=0","-ferror-limit=1000","-x","c++","C:\\msys64\\home\\dyl\\Codes\\qt\\Snake\\mainwindow.cpp"],"directory":"C:/msys64/home/dyl/Codes/qt/Snake/build/Desktop_Qt_6_7_3_MinGW_64_bit-Debug/.qtc_clangd","file":"C:/msys64/home/dyl/Codes/qt/Snake/mainwindow.cpp"},{"arguments":["clang","-Wno-documentation-unknown-command","-Wno-unknown-warning-option","-Wno-unknown-pragmas","-nostdinc","-nostdinc++","-DQT_QML_DEBUG","-g","-std=gnu++17","-fdiagnostics-color=always","-fsyntax-only","-m64","--target=x86_64-w64-mingw32","-DMINGW_HAS_SECURE_API","-DQT_CORE_LIB","-DQT_GUI_LIB","-DQT_NEEDS_QMAIN","-DQT_WIDGETS_LIB","-DUNICODE","-DWIN32","-DWIN64","-D_ENABLE_EXTENDED_ALIGNED_STORAGE","-D_UNICODE","-D_WIN64","-DQ_CREATOR_RUN","-DQT_ANNOTATE_FUNCTION(x)=__attribute__((annotate(#x)))","-IC:\\thely\\Qt\\Tools\\QtCreator\\share\\qtcreator\\cplusplus\\wrappedMingwHeaders","-IC:\\thely\\Qt\\Tools\\QtCreator\\share\\qtcreator\\cplusplus\\wrappedQtHeaders","-IC:\\thely\\Qt\\Tools\\QtCreator\\share\\qtcreator\\cplusplus\\wrappedQtHeaders\\QtCore","-IC:\\msys64\\home\\dyl\\Codes\\qt\\Snake\\build\\Desktop_Qt_6_7_3_MinGW_64_bit-Debug\\Snake_autogen\\include","-isystem","C:\\thely\\Qt\\6.7.3\\mingw_64\\include\\QtCore","-isystem","C:\\thely\\Qt\\6.7.3\\mingw_64\\include","-isystem","C:\\thely\\Qt\\6.7.3\\mingw_64\\mkspecs\\win32-g++","-isystem","C:\\thely\\Qt\\6.7.3\\mingw_64\\include\\QtWidgets","-isystem","C:\\thely\\Qt\\6.7.3\\mingw_64\\include\\QtGui","-isystem","C:\\thely\\Qt\\Tools\\mingw1120_64\\lib\\gcc\\x86_64-w64-mingw32\\11.2.0\\include\\c++","-isystem","C:\\thely\\Qt\\Tools\\mingw1120_64\\lib\\gcc\\x86_64-w64-mingw32\\11.2.0\\include\\c++\\x86_64-w64-mingw32","-isystem","C:\\thely\\Qt\\Tools\\mingw1120_64\\lib\\gcc\\x86_64-w64-mingw32\\11.2.0\\include\\c++\\backward","-isystem","C:\\thely\\Qt\\Tools\\QtCreator\\bin\\clang\\lib\\clang\\18\\include","-isystem","C:\\thely\\Qt\\Tools\\mingw1120_64\\x86_64-w64-mingw32\\include","-fmessage-length=0","-fdiagnostics-show-note-include-stack","-fretain-comments-from-system-headers","-fmacro-backtrace-limit=0","-ferror-limit=1000","-x","c++","C:\\msys64\\home\\dyl\\Codes\\qt\\Snake\\CustomBtn.cpp"],"directory":"C:/msys64/home/dyl/Codes/qt/Snake/build/Desktop_Qt_6_7_3_MinGW_64_bit-Debug/.qtc_clangd","file":"C:/msys64/home/dyl/Codes/qt/Snake/CustomBtn.cpp"},{"arguments":["clang","-Wno-documentation-unknown-command","-Wno-unknown-warning-option","-Wno-unknown-pragmas","-nostdinc","-nostdinc++","-DQT_QML_DEBUG","-g","-std=gnu++17","-fdiagnostics-color=always","-fsyntax-only","-m64","--target=x86_64-w64-mingw32","-DMINGW_HAS_SECURE_API","-DQT_CORE_LIB","-DQT_GUI_LIB","-DQT_NEEDS_QMAIN","-DQT_WIDGETS_LIB","-DUNICODE","-DWIN32","-DWIN64","-D_ENABLE_EXTENDED_ALIGNED_STORAGE","-D_UNICODE","-D_WIN64","-DQ_CREATOR_RUN","-DQT_ANNOTATE_FUNCTION(x)=__attribute__((annotate(#x)))","-IC:\\thely\\Qt\\Tools\\QtCreator\\share\\qtcreator\\cplusplus\\wrappedMingwHeaders","-IC:\\thely\\Qt\\Tools\\QtCreator\\share\\qtcreator\\cplusplus\\wrappedQtHeaders","-IC:\\thely\\Qt\\Tools\\QtCreator\\share\\qtcreator\\cplusplus\\wrappedQtHeaders\\QtCore","-IC:\\msys64\\home\\dyl\\Codes\\qt\\Snake\\build\\Desktop_Qt_6_7_3_MinGW_64_bit-Debug\\Snake_autogen\\include","-isystem","C:\\thely\\Qt\\6.7.3\\mingw_64\\include\\QtCore","-isystem","C:\\thely\\Qt\\6.7.3\\mingw_64\\include","-isystem","C:\\thely\\Qt\\6.7.3\\mingw_64\\mkspecs\\win32-g++","-isystem","C:\\thely\\Qt\\6.7.3\\mingw_64\\include\\QtWidgets","-isystem","C:\\thely\\Qt\\6.7.3\\mingw_64\\include\\QtGui","-isystem","C:\\thely\\Qt\\Tools\\mingw1120_64\\lib\\gcc\\x86_64-w64-mingw32\\11.2.0\\include\\c++","-isystem","C:\\thely\\Qt\\Tools\\mingw1120_64\\lib\\gcc\\x86_64-w64-mingw32\\11.2.0\\include\\c++\\x86_64-w64-mingw32","-isystem","C:\\thely\\Qt\\Tools\\mingw1120_64\\lib\\gcc\\x86_64-w64-mingw32\\11.2.0\\include\\c++\\backward","-isystem","C:\\thely\\Qt\\Tools\\QtCreator\\bin\\clang\\lib\\clang\\18\\include","-isystem","C:\\thely\\Qt\\Tools\\mingw1120_64\\x86_64-w64-mingw32\\include","-fmessage-length=0","-fdiagnostics-show-note-include-stack","-fretain-comments-from-system-headers","-fmacro-backtrace-limit=0","-ferror-limit=1000","-x","c++","C:\\msys64\\home\\dyl\\Codes\\qt\\Snake\\snake.cpp"],"directory":"C:/msys64/home/dyl/Codes/qt/Snake/build/Desktop_Qt_6_7_3_MinGW_64_bit-Debug/.qtc_clangd","file":"C:/msys64/home/dyl/Codes/qt/Snake/snake.cpp"},{"arguments":["clang","-Wno-documentation-unknown-command","-Wno-unknown-warning-option","-Wno-unknown-pragmas","-nostdinc","-nostdinc++","-DQT_QML_DEBUG","-g","-std=gnu++17","-fdiagnostics-color=always","-fsyntax-only","-m64","--target=x86_64-w64-mingw32","-DMINGW_HAS_SECURE_API","-DQT_CORE_LIB","-DQT_GUI_LIB","-DQT_NEEDS_QMAIN","-DQT_WIDGETS_LIB","-DUNICODE","-DWIN32","-DWIN64","-D_ENABLE_EXTENDED_ALIGNED_STORAGE","-D_UNICODE","-D_WIN64","-DQ_CREATOR_RUN","-DQT_ANNOTATE_FUNCTION(x)=__attribute__((annotate(#x)))","-IC:\\thely\\Qt\\Tools\\QtCreator\\share\\qtcreator\\cplusplus\\wrappedMingwHeaders","-IC:\\thely\\Qt\\Tools\\QtCreator\\share\\qtcreator\\cplusplus\\wrappedQtHeaders","-IC:\\thely\\Qt\\Tools\\QtCreator\\share\\qtcreator\\cplusplus\\wrappedQtHeaders\\QtCore","-IC:\\msys64\\home\\dyl\\Codes\\qt\\Snake\\build\\Desktop_Qt_6_7_3_MinGW_64_bit-Debug\\Snake_autogen\\include","-isystem","C:\\thely\\Qt\\6.7.3\\mingw_64\\include\\QtCore","-isystem","C:\\thely\\Qt\\6.7.3\\mingw_64\\include","-isystem","C:\\thely\\Qt\\6.7.3\\mingw_64\\mkspecs\\win32-g++","-isystem","C:\\thely\\Qt\\6.7.3\\mingw_64\\include\\QtWidgets","-isystem","C:\\thely\\Qt\\6.7.3\\mingw_64\\include\\QtGui","-isystem","C:\\thely\\Qt\\Tools\\mingw1120_64\\lib\\gcc\\x86_64-w64-mingw32\\11.2.0\\include\\c++","-isystem","C:\\thely\\Qt\\Tools\\mingw1120_64\\lib\\gcc\\x86_64-w64-mingw32\\11.2.0\\include\\c++\\x86_64-w64-mingw32","-isystem","C:\\thely\\Qt\\Tools\\mingw1120_64\\lib\\gcc\\x86_64-w64-mingw32\\11.2.0\\include\\c++\\backward","-isystem","C:\\thely\\Qt\\Tools\\QtCreator\\bin\\clang\\lib\\clang\\18\\include","-isystem","C:\\thely\\Qt\\Tools\\mingw1120_64\\x86_64-w64-mingw32\\include","-fmessage-length=0","-fdiagnostics-show-note-include-stack","-fretain-comments-from-system-headers","-fmacro-backtrace-limit=0","-ferror-limit=1000","-x","c++","C:\\msys64\\home\\dyl\\Codes\\qt\\Snake\\board.cpp"],"directory":"C:/msys64/home/dyl/Codes/qt/Snake/build/Desktop_Qt_6_7_3_MinGW_64_bit-Debug/.qtc_clangd","file":"C:/msys64/home/dyl/Codes/qt/Snake/board.cpp"},{"arguments":["clang","-Wno-documentation-unknown-command","-Wno-unknown-warning-option","-Wno-unknown-pragmas","-nostdinc","-nostdinc++","-DQT_QML_DEBUG","-g","-std=gnu++17","-fdiagnostics-color=always","-fsyntax-only","-m64","--target=x86_64-w64-mingw32","-DMINGW_HAS_SECURE_API","-DQT_CORE_LIB","-DQT_GUI_LIB","-DQT_NEEDS_QMAIN","-DQT_WIDGETS_LIB","-DUNICODE","-DWIN32","-DWIN64","-D_ENABLE_EXTENDED_ALIGNED_STORAGE","-D_UNICODE","-D_WIN64","-DQ_CREATOR_RUN","-DQT_ANNOTATE_FUNCTION(x)=__attribute__((annotate(#x)))","-IC:\\thely\\Qt\\Tools\\QtCreator\\share\\qtcreator\\cplusplus\\wrappedMingwHeaders","-IC:\\thely\\Qt\\Tools\\QtCreator\\share\\qtcreator\\cplusplus\\wrappedQtHeaders","-IC:\\thely\\Qt\\Tools\\QtCreator\\share\\qtcreator\\cplusplus\\wrappedQtHeaders\\QtCore","-IC:\\msys64\\home\\dyl\\Codes\\qt\\Snake\\build\\Desktop_Qt_6_7_3_MinGW_64_bit-Debug\\Snake_autogen\\include","-isystem","C:\\thely\\Qt\\6.7.3\\mingw_64\\include\\QtCore","-isystem","C:\\thely\\Qt\\6.7.3\\mingw_64\\include","-isystem","C:\\thely\\Qt\\6.7.3\\mingw_64\\mkspecs\\win32-g++","-isystem","C:\\thely\\Qt\\6.7.3\\mingw_64\\include\\QtWidgets","-isystem","C:\\thely\\Qt\\6.7.3\\mingw_64\\include\\QtGui","-isystem","C:\\thely\\Qt\\Tools\\mingw1120_64\\lib\\gcc\\x86_64-w64-mingw32\\11.2.0\\include\\c++","-isystem","C:\\thely\\Qt\\Tools\\mingw1120_64\\lib\\gcc\\x86_64-w64-mingw32\\11.2.0\\include\\c++\\x86_64-w64-mingw32","-isystem","C:\\thely\\Qt\\Tools\\mingw1120_64\\lib\\gcc\\x86_64-w64-mingw32\\11.2.0\\include\\c++\\backward","-isystem","C:\\thely\\Qt\\Tools\\QtCreator\\bin\\clang\\lib\\clang\\18\\include","-isystem","C:\\thely\\Qt\\Tools\\mingw1120_64\\x86_64-w64-mingw32\\include","-fmessage-length=0","-fdiagnostics-show-note-include-stack","-fretain-comments-from-system-headers","-fmacro-backtrace-limit=0","-ferror-limit=1000","-x","c++","C:\\msys64\\home\\dyl\\Codes\\qt\\Snake\\gameboardview.cpp"],"directory":"C:/msys64/home/dyl/Codes/qt/Snake/build/Desktop_Qt_6_7_3_MinGW_64_bit-Debug/.qtc_clangd","file":"C:/msys64/home/dyl/Codes/qt/Snake/gameboardview.cpp"},{"arguments":["clang","-Wno-documentation-unknown-command","-Wno-unknown-warning-option","-Wno-unknown-pragmas","-nostdinc","-nostdinc++","-DQT_QML_DEBUG","-g","-std=gnu++17","-fdiagnostics-color=always","-fsyntax-only","-m64","--target=x86_64-w64-mingw32","-DMINGW_HAS_SECURE_API","-DQT_CORE_LIB","-DQT_GUI_LIB","-DQT_NEEDS_QMAIN","-DQT_WIDGETS_LIB","-DUNICODE","-DWIN32","-DWIN64","-D_ENABLE_EXTENDED_ALIGNED_STORAGE","-D_UNICODE","-D_WIN64","-DQ_CREATOR_RUN","-DQT_ANNOTATE_FUNCTION(x)=__attribute__((annotate(#x)))","-IC:\\thely\\Qt\\Tools\\QtCreator\\share\\qtcreator\\cplusplus\\wrappedMingwHeaders","-IC:\\thely\\Qt\\Tools\\QtCreator\\share\\qtcreator\\cplusplus\\wrappedQtHeaders","-IC:\\thely\\Qt\\Tools\\QtCreator\\share\\qtcreator\\cplusplus\\wrappedQtHeaders\\QtCore","-IC:\\msys64\\home\\dyl\\Codes\\qt\\Snake\\build\\Desktop_Qt_6_7_3_MinGW_64_bit-Debug\\Snake_autogen\\include","-isystem","C:\\thely\\Qt\\6.7.3\\mingw_64\\include\\QtCore","-isystem","C:\\thely\\Qt\\6.7.3\\mingw_64\\include","-isystem","C:\\thely\\Qt\\6.7.3\\mingw_64\\mkspecs\\win32-g++","-isystem","C:\\thely\\Qt\\6.7.3\\mingw_64\\include\\QtWidgets","-isystem","C:\\thely\\Qt\\6.7.3\\mingw_64\\include\\QtGui","-isystem","C:\\thely\\Qt\\Tools\\mingw1120_64\\lib\\gcc\\x86_64-w64-mingw32\\11.2.0\\include\\c++","-isystem","C:\\thely\\Qt\\Tools\\mingw1120_64\\lib\\gcc\\x86_64-w64-mingw32\\11.2.0\\include\\c++\\x86_64-w64-mingw32","-isystem","C:\\thely\\Qt\\Tools\\mingw1120_64\\lib\\gcc\\x86_64-w64-mingw32\\11.2.0\\include\\c++\\backward","-isystem","C:\\thely\\Qt\\Tools\\QtCreator\\bin\\clang\\lib\\clang\\18\\include","-isystem","C:\\thely\\Qt\\Tools\\mingw1120_64\\x86_64-w64-mingw32\\include","-fmessage-length=0","-fdiagnostics-show-note-include-stack","-fretain-comments-from-system-headers","-fmacro-backtrace-limit=0","-ferror-limit=1000","-x","c++","C:\\msys64\\home\\dyl\\Codes\\qt\\Snake\\introwindow.cpp"],"directory":"C:/msys64/home/dyl/Codes/qt/Snake/build/Desktop_Qt_6_7_3_MinGW_64_bit-Debug/.qtc_clangd","file":"C:/msys64/home/dyl/Codes/qt/Snake/introwindow.cpp"},{"arguments":["clang","-Wno-documentation-unknown-command","-Wno-unknown-warning-option","-Wno-unknown-pragmas","-nostdinc","-nostdinc++","-DQT_QML_DEBUG","-g","-std=gnu++17","-fdiagnostics-color=always","-fsyntax-only","-m64","--target=x86_64-w64-mingw32","-DMINGW_HAS_SECURE_API","-DQT_CORE_LIB","-DQT_GUI_LIB","-DQT_NEEDS_QMAIN","-DQT_WIDGETS_LIB","-DUNICODE","-DWIN32","-DWIN64","-D_ENABLE_EXTENDED_ALIGNED_STORAGE","-D_UNICODE","-D_WIN64","-DQ_CREATOR_RUN","-DQT_ANNOTATE_FUNCTION(x)=__attribute__((annotate(#x)))","-IC:\\thely\\Qt\\Tools\\QtCreator\\share\\qtcreator\\cplusplus\\wrappedMingwHeaders","-IC:\\thely\\Qt\\Tools\\QtCreator\\share\\qtcreator\\cplusplus\\wrappedQtHeaders","-IC:\\thely\\Qt\\Tools\\QtCreator\\share\\qtcreator\\cplusplus\\wrappedQtHeaders\\QtCore","-IC:\\msys64\\home\\dyl\\Codes\\qt\\Snake\\build\\Desktop_Qt_6_7_3_MinGW_64_bit-Debug\\Snake_autogen\\include","-isystem","C:\\thely\\Qt\\6.7.3\\mingw_64\\include\\QtCore","-isystem","C:\\thely\\Qt\\6.7.3\\mingw_64\\include","-isystem","C:\\thely\\Qt\\6.7.3\\mingw_64\\mkspecs\\win32-g++","-isystem","C:\\thely\\Qt\\6.7.3\\mingw_64\\include\\QtWidgets","-isystem","C:\\thely\\Qt\\6.7.3\\mingw_64\\include\\QtGui","-isystem","C:\\thely\\Qt\\Tools\\mingw1120_64\\lib\\gcc\\x86_64-w64-mingw32\\11.2.0\\include\\c++","-isystem","C:\\thely\\Qt\\Tools\\mingw1120_64\\lib\\gcc\\x86_64-w64-mingw32\\11.2.0\\include\\c++\\x86_64-w64-mingw32","-isystem","C:\\thely\\Qt\\Tools\\mingw1120_64\\lib\\gcc\\x86_64-w64-mingw32\\11.2.0\\include\\c++\\backward","-isystem","C:\\thely\\Qt\\Tools\\QtCreator\\bin\\clang\\lib\\clang\\18\\include","-isystem","C:\\thely\\Qt\\Tools\\mingw1120_64\\x86_64-w64-mingw32\\include","-fmessage-length=0","-fdiagnostics-show-note-include-stack","-fretain-comments-from-system-headers","-fmacro-backtrace-limit=0","-ferror-limit=1000","-x","c++-header","C:\\msys64\\home\\dyl\\Codes\\qt\\Snake\\mainwindow.h"],"directory":"C:/msys64/home/dyl/Codes/qt/Snake/build/Desktop_Qt_6_7_3_MinGW_64_bit-Debug/.qtc_clangd","file":"C:/msys64/home/dyl/Codes/qt/Snake/mainwindow.h"},{"arguments":["clang","-Wno-documentation-unknown-command","-Wno-unknown-warning-option","-Wno-unknown-pragmas","-nostdinc","-nostdinc++","-DQT_QML_DEBUG","-g","-std=gnu++17","-fdiagnostics-color=always","-fsyntax-only","-m64","--target=x86_64-w64-mingw32","-DMINGW_HAS_SECURE_API","-DQT_CORE_LIB","-DQT_GUI_LIB","-DQT_NEEDS_QMAIN","-DQT_WIDGETS_LIB","-DUNICODE","-DWIN32","-DWIN64","-D_ENABLE_EXTENDED_ALIGNED_STORAGE","-D_UNICODE","-D_WIN64","-DQ_CREATOR_RUN","-DQT_ANNOTATE_FUNCTION(x)=__attribute__((annotate(#x)))","-IC:\\thely\\Qt\\Tools\\QtCreator\\share\\qtcreator\\cplusplus\\wrappedMingwHeaders","-IC:\\thely\\Qt\\Tools\\QtCreator\\share\\qtcreator\\cplusplus\\wrappedQtHeaders","-IC:\\thely\\Qt\\Tools\\QtCreator\\share\\qtcreator\\cplusplus\\wrappedQtHeaders\\QtCore","-IC:\\msys64\\home\\dyl\\Codes\\qt\\Snake\\build\\Desktop_Qt_6_7_3_MinGW_64_bit-Debug\\Snake_autogen\\include","-isystem","C:\\thely\\Qt\\6.7.3\\mingw_64\\include\\QtCore","-isystem","C:\\thely\\Qt\\6.7.3\\mingw_64\\include","-isystem","C:\\thely\\Qt\\6.7.3\\mingw_64\\mkspecs\\win32-g++","-isystem","C:\\thely\\Qt\\6.7.3\\mingw_64\\include\\QtWidgets","-isystem","C:\\thely\\Qt\\6.7.3\\mingw_64\\include\\QtGui","-isystem","C:\\thely\\Qt\\Tools\\mingw1120_64\\lib\\gcc\\x86_64-w64-mingw32\\11.2.0\\include\\c++","-isystem","C:\\thely\\Qt\\Tools\\mingw1120_64\\lib\\gcc\\x86_64-w64-mingw32\\11.2.0\\include\\c++\\x86_64-w64-mingw32","-isystem","C:\\thely\\Qt\\Tools\\mingw1120_64\\lib\\gcc\\x86_64-w64-mingw32\\11.2.0\\include\\c++\\backward","-isystem","C:\\thely\\Qt\\Tools\\QtCreator\\bin\\clang\\lib\\clang\\18\\include","-isystem","C:\\thely\\Qt\\Tools\\mingw1120_64\\x86_64-w64-mingw32\\include","-fmessage-length=0","-fdiagnostics-show-note-include-stack","-fretain-comments-from-system-headers","-fmacro-backtrace-limit=0","-ferror-limit=1000","-x","c++-header","C:\\msys64\\home\\dyl\\Codes\\qt\\Snake\\CustomBtn.h"],"directory":"C:/msys64/home/dyl/Codes/qt/Snake/build/Desktop_Qt_6_7_3_MinGW_64_bit-Debug/.qtc_clangd","file":"C:/msys64/home/dyl/Codes/qt/Snake/CustomBtn.h"},{"arguments":["clang","-Wno-documentation-unknown-command","-Wno-unknown-warning-option","-Wno-unknown-pragmas","-nostdinc","-nostdinc++","-DQT_QML_DEBUG","-g","-std=gnu++17","-fdiagnostics-color=always","-fsyntax-only","-m64","--target=x86_64-w64-mingw32","-DMINGW_HAS_SECURE_API","-DQT_CORE_LIB","-DQT_GUI_LIB","-DQT_NEEDS_QMAIN","-DQT_WIDGETS_LIB","-DUNICODE","-DWIN32","-DWIN64","-D_ENABLE_EXTENDED_ALIGNED_STORAGE","-D_UNICODE","-D_WIN64","-DQ_CREATOR_RUN","-DQT_ANNOTATE_FUNCTION(x)=__attribute__((annotate(#x)))","-IC:\\thely\\Qt\\Tools\\QtCreator\\share\\qtcreator\\cplusplus\\wrappedMingwHeaders","-IC:\\thely\\Qt\\Tools\\QtCreator\\share\\qtcreator\\cplusplus\\wrappedQtHeaders","-IC:\\thely\\Qt\\Tools\\QtCreator\\share\\qtcreator\\cplusplus\\wrappedQtHeaders\\QtCore","-IC:\\msys64\\home\\dyl\\Codes\\qt\\Snake\\build\\Desktop_Qt_6_7_3_MinGW_64_bit-Debug\\Snake_autogen\\include","-isystem","C:\\thely\\Qt\\6.7.3\\mingw_64\\include\\QtCore","-isystem","C:\\thely\\Qt\\6.7.3\\mingw_64\\include","-isystem","C:\\thely\\Qt\\6.7.3\\mingw_64\\mkspecs\\win32-g++","-isystem","C:\\thely\\Qt\\6.7.3\\mingw_64\\include\\QtWidgets","-isystem","C:\\thely\\Qt\\6.7.3\\mingw_64\\include\\QtGui","-isystem","C:\\thely\\Qt\\Tools\\mingw1120_64\\lib\\gcc\\x86_64-w64-mingw32\\11.2.0\\include\\c++","-isystem","C:\\thely\\Qt\\Tools\\mingw1120_64\\lib\\gcc\\x86_64-w64-mingw32\\11.2.0\\include\\c++\\x86_64-w64-mingw32","-isystem","C:\\thely\\Qt\\Tools\\mingw1120_64\\lib\\gcc\\x86_64-w64-mingw32\\11.2.0\\include\\c++\\backward","-isystem","C:\\thely\\Qt\\Tools\\QtCreator\\bin\\clang\\lib\\clang\\18\\include","-isystem","C:\\thely\\Qt\\Tools\\mingw1120_64\\x86_64-w64-mingw32\\include","-fmessage-length=0","-fdiagnostics-show-note-include-stack","-fretain-comments-from-system-headers","-fmacro-backtrace-limit=0","-ferror-limit=1000","-x","c++-header","C:\\msys64\\home\\dyl\\Codes\\qt\\Snake\\snake.h"],"directory":"C:/msys64/home/dyl/Codes/qt/Snake/build/Desktop_Qt_6_7_3_MinGW_64_bit-Debug/.qtc_clangd","file":"C:/msys64/home/dyl/Codes/qt/Snake/snake.h"},{"arguments":["clang","-Wno-documentation-unknown-command","-Wno-unknown-warning-option","-Wno-unknown-pragmas","-nostdinc","-nostdinc++","-DQT_QML_DEBUG","-g","-std=gnu++17","-fdiagnostics-color=always","-fsyntax-only","-m64","--target=x86_64-w64-mingw32","-DMINGW_HAS_SECURE_API","-DQT_CORE_LIB","-DQT_GUI_LIB","-DQT_NEEDS_QMAIN","-DQT_WIDGETS_LIB","-DUNICODE","-DWIN32","-DWIN64","-D_ENABLE_EXTENDED_ALIGNED_STORAGE","-D_UNICODE","-D_WIN64","-DQ_CREATOR_RUN","-DQT_ANNOTATE_FUNCTION(x)=__attribute__((annotate(#x)))","-IC:\\thely\\Qt\\Tools\\QtCreator\\share\\qtcreator\\cplusplus\\wrappedMingwHeaders","-IC:\\thely\\Qt\\Tools\\QtCreator\\share\\qtcreator\\cplusplus\\wrappedQtHeaders","-IC:\\thely\\Qt\\Tools\\QtCreator\\share\\qtcreator\\cplusplus\\wrappedQtHeaders\\QtCore","-IC:\\msys64\\home\\dyl\\Codes\\qt\\Snake\\build\\Desktop_Qt_6_7_3_MinGW_64_bit-Debug\\Snake_autogen\\include","-isystem","C:\\thely\\Qt\\6.7.3\\mingw_64\\include\\QtCore","-isystem","C:\\thely\\Qt\\6.7.3\\mingw_64\\include","-isystem","C:\\thely\\Qt\\6.7.3\\mingw_64\\mkspecs\\win32-g++","-isystem","C:\\thely\\Qt\\6.7.3\\mingw_64\\include\\QtWidgets","-isystem","C:\\thely\\Qt\\6.7.3\\mingw_64\\include\\QtGui","-isystem","C:\\thely\\Qt\\Tools\\mingw1120_64\\lib\\gcc\\x86_64-w64-mingw32\\11.2.0\\include\\c++","-isystem","C:\\thely\\Qt\\Tools\\mingw1120_64\\lib\\gcc\\x86_64-w64-mingw32\\11.2.0\\include\\c++\\x86_64-w64-mingw32","-isystem","C:\\thely\\Qt\\Tools\\mingw1120_64\\lib\\gcc\\x86_64-w64-mingw32\\11.2.0\\include\\c++\\backward","-isystem","C:\\thely\\Qt\\Tools\\QtCreator\\bin\\clang\\lib\\clang\\18\\include","-isystem","C:\\thely\\Qt\\Tools\\mingw1120_64\\x86_64-w64-mingw32\\include","-fmessage-length=0","-fdiagnostics-show-note-include-stack","-fretain-comments-from-system-headers","-fmacro-backtrace-limit=0","-ferror-limit=1000","-x","c++-header","C:\\msys64\\home\\dyl\\Codes\\qt\\Snake\\board.h"],"directory":"C:/msys64/home/dyl/Codes/qt/Snake/build/Desktop_Qt_6_7_3_MinGW_64_bit-Debug/.qtc_clangd","file":"C:/msys64/home/dyl/Codes/qt/Snake/board.h"},{"arguments":["clang","-Wno-documentation-unknown-command","-Wno-unknown-warning-option","-Wno-unknown-pragmas","-nostdinc","-nostdinc++","-DQT_QML_DEBUG","-g","-std=gnu++17","-fdiagnostics-color=always","-fsyntax-only","-m64","--target=x86_64-w64-mingw32","-DMINGW_HAS_SECURE_API","-DQT_CORE_LIB","-DQT_GUI_LIB","-DQT_NEEDS_QMAIN","-DQT_WIDGETS_LIB","-DUNICODE","-DWIN32","-DWIN64","-D_ENABLE_EXTENDED_ALIGNED_STORAGE","-D_UNICODE","-D_WIN64","-DQ_CREATOR_RUN","-DQT_ANNOTATE_FUNCTION(x)=__attribute__((annotate(#x)))","-IC:\\thely\\Qt\\Tools\\QtCreator\\share\\qtcreator\\cplusplus\\wrappedMingwHeaders","-IC:\\thely\\Qt\\Tools\\QtCreator\\share\\qtcreator\\cplusplus\\wrappedQtHeaders","-IC:\\thely\\Qt\\Tools\\QtCreator\\share\\qtcreator\\cplusplus\\wrappedQtHeaders\\QtCore","-IC:\\msys64\\home\\dyl\\Codes\\qt\\Snake\\build\\Desktop_Qt_6_7_3_MinGW_64_bit-Debug\\Snake_autogen\\include","-isystem","C:\\thely\\Qt\\6.7.3\\mingw_64\\include\\QtCore","-isystem","C:\\thely\\Qt\\6.7.3\\mingw_64\\include","-isystem","C:\\thely\\Qt\\6.7.3\\mingw_64\\mkspecs\\win32-g++","-isystem","C:\\thely\\Qt\\6.7.3\\mingw_64\\include\\QtWidgets","-isystem","C:\\thely\\Qt\\6.7.3\\mingw_64\\include\\QtGui","-isystem","C:\\thely\\Qt\\Tools\\mingw1120_64\\lib\\gcc\\x86_64-w64-mingw32\\11.2.0\\include\\c++","-isystem","C:\\thely\\Qt\\Tools\\mingw1120_64\\lib\\gcc\\x86_64-w64-mingw32\\11.2.0\\include\\c++\\x86_64-w64-mingw32","-isystem","C:\\thely\\Qt\\Tools\\mingw1120_64\\lib\\gcc\\x86_64-w64-mingw32\\11.2.0\\include\\c++\\backward","-isystem","C:\\thely\\Qt\\Tools\\QtCreator\\bin\\clang\\lib\\clang\\18\\include","-isystem","C:\\thely\\Qt\\Tools\\mingw1120_64\\x86_64-w64-mingw32\\include","-fmessage-length=0","-fdiagnostics-show-note-include-stack","-fretain-comments-from-system-headers","-fmacro-backtrace-limit=0","-ferror-limit=1000","-x","c++-header","C:\\msys64\\home\\dyl\\Codes\\qt\\Snake\\gameboardview.h"],"directory":"C:/msys64/home/dyl/Codes/qt/Snake/build/Desktop_Qt_6_7_3_MinGW_64_bit-Debug/.qtc_clangd","file":"C:/msys64/home/dyl/Codes/qt/Snake/gameboardview.h"},{"arguments":["clang","-Wno-documentation-unknown-command","-Wno-unknown-warning-option","-Wno-unknown-pragmas","-nostdinc","-nostdinc++","-DQT_QML_DEBUG","-g","-std=gnu++17","-fdiagnostics-color=always","-fsyntax-only","-m64","--target=x86_64-w64-mingw32","-DMINGW_HAS_SECURE_API","-DQT_CORE_LIB","-DQT_GUI_LIB","-DQT_NEEDS_QMAIN","-DQT_WIDGETS_LIB","-DUNICODE","-DWIN32","-DWIN64","-D_ENABLE_EXTENDED_ALIGNED_STORAGE","-D_UNICODE","-D_WIN64","-DQ_CREATOR_RUN","-DQT_ANNOTATE_FUNCTION(x)=__attribute__((annotate(#x)))","-IC:\\thely\\Qt\\Tools\\QtCreator\\share\\qtcreator\\cplusplus\\wrappedMingwHeaders","-IC:\\thely\\Qt\\Tools\\QtCreator\\share\\qtcreator\\cplusplus\\wrappedQtHeaders","-IC:\\thely\\Qt\\Tools\\QtCreator\\share\\qtcreator\\cplusplus\\wrappedQtHeaders\\QtCore","-IC:\\msys64\\home\\dyl\\Codes\\qt\\Snake\\build\\Desktop_Qt_6_7_3_MinGW_64_bit-Debug\\Snake_autogen\\include","-isystem","C:\\thely\\Qt\\6.7.3\\mingw_64\\include\\QtCore","-isystem","C:\\thely\\Qt\\6.7.3\\mingw_64\\include","-isystem","C:\\thely\\Qt\\6.7.3\\mingw_64\\mkspecs\\win32-g++","-isystem","C:\\thely\\Qt\\6.7.3\\mingw_64\\include\\QtWidgets","-isystem","C:\\thely\\Qt\\6.7.3\\mingw_64\\include\\QtGui","-isystem","C:\\thely\\Qt\\Tools\\mingw1120_64\\lib\\gcc\\x86_64-w64-mingw32\\11.2.0\\include\\c++","-isystem","C:\\thely\\Qt\\Tools\\mingw1120_64\\lib\\gcc\\x86_64-w64-mingw32\\11.2.0\\include\\c++\\x86_64-w64-mingw32","-isystem","C:\\thely\\Qt\\Tools\\mingw1120_64\\lib\\gcc\\x86_64-w64-mingw32\\11.2.0\\include\\c++\\backward","-isystem","C:\\thely\\Qt\\Tools\\QtCreator\\bin\\clang\\lib\\clang\\18\\include","-isystem","C:\\thely\\Qt\\Tools\\mingw1120_64\\x86_64-w64-mingw32\\include","-fmessage-length=0","-fdiagnostics-show-note-include-stack","-fretain-comments-from-system-headers","-fmacro-backtrace-limit=0","-ferror-limit=1000","-x","c++-header","C:\\msys64\\home\\dyl\\Codes\\qt\\Snake\\introwindow.h"],"directory":"C:/msys64/home/dyl/Codes/qt/Snake/build/Desktop_Qt_6_7_3_MinGW_64_bit-Debug/.qtc_clangd","file":"C:/msys64/home/dyl/Codes/qt/Snake/introwindow.h"}]